{
  "prediction_date": "2025-05-04",
  "most_volatile_coin": "chainlink",
  "predictions": [
    {
      "coin": "chainlink",
      "volatility_probability": 0.37045
    },
    {
      "coin": "ethereum",
      "volatility_probability": 0.36608
    },
    {
      "coin": "bitcoin",
      "volatility_probability": 0.362295
    },
    {
      "coin": "cardano",
      "volatility_probability": 0.286713
    },
    {
      "coin": "tron",
      "volatility_probability": 0.254542
    },
    {
      "coin": "litecoin",
      "volatility_probability": 0.218614
    },
    {
      "coin": "theta-token",
      "volatility_probability": 0.206544
    },
    {
      "coin": "binancecoin",
      "volatility_probability": 0.179477
    },
    {
      "coin": "dogecoin",
      "volatility_probability": 0.167088
    },
    {
      "coin": "avalanche-2",
      "volatility_probability": 0.16642
    },
    {
      "coin": "ripple",
      "volatility_probability": 0.141633
    },
    {
      "coin": "solana",
      "volatility_probability": 0.118999
    },
    {
      "coin": "algorand",
      "volatility_probability": 0.097248
    },
    {
      "coin": "matic-network",
      "volatility_probability": 0.066494
    },
    {
      "coin": "stellar",
      "volatility_probability": 0.062913
    },
    {
      "coin": "polkadot",
      "volatility_probability": 0.062307
    },
    {
      "coin": "cosmos",
      "volatility_probability": 0.061107
    },
    {
      "coin": "vechain",
      "volatility_probability": 0.044737
    }
  ]
}